iptoolsjj/__init__.py
iptoolsjj/iptoolsjj.py
iptoolsjj-1.4.2.dist-info/DESCRIPTION.rst
iptoolsjj-1.4.2.dist-info/METADATA
iptoolsjj-1.4.2.dist-info/RECORD
iptoolsjj-1.4.2.dist-info/WHEEL
iptoolsjj-1.4.2.dist-info/metadata.json
iptoolsjj-1.4.2.dist-info/top_level.txt
