Metadata-Version: 2.0
Name: iptoolsjj
Version: 1.4.2
Summary: IP Tools
Home-page: https://github.com/jarekj9/iptoolsjj
Author: Jaroslaw Jankun
Author-email: jaroslaw.jankun@gmail.com
License: MIT
Platform: UNKNOWN
